steam_sales/__init__.py
steam_sales/_version.py
steam_sales/app.py
steam_sales/steam_etl/__init__.py
steam_sales/steam_etl/cleaner.py
steam_sales/steam_etl/crud.py
steam_sales/steam_etl/db.py
steam_sales/steam_etl/fetcher.py
steam_sales/steam_etl/model.py
steam_sales/steam_etl/settings.py
steam_sales/steam_etl/utils.py
steam_sales/steam_etl/validation.py
steam_sales/steam_etl/sql/get_all_game_data.sql
steam_sales/steam_etl/sql/get_all_steam_data.sql
steam_sales/steam_etl/sql/get_all_steamspy_data.sql
steam_sales/steam_etl/sql/get_new_steam_data.sql
steam_sales/steam_etl/sql/get_new_steamspy_data.sql
steam_sales/steam_etl/sql/steam_appid_dup.sql
steam_sales/steam_etl/sql/steamspy_appid_dup.sql
steamstore_etl-0.0.15.dist-info/LICENSE
steamstore_etl-0.0.15.dist-info/METADATA
steamstore_etl-0.0.15.dist-info/WHEEL
steamstore_etl-0.0.15.dist-info/entry_points.txt
steamstore_etl-0.0.15.dist-info/top_level.txt
steamstore_etl-0.0.15.dist-info/RECORD
