Metadata-Version: 2.1
Name: steamstore_etl
Version: 0.0.15
Summary: CLI for Steam Store Data Ingestion ETL Pipeline
Home-page: https://github.com/DataForgeOpenAIHub/Steam-Sales-Analysis
Author: DataForgeOpenAIHub
License: MIT
Keywords: steam,etl,data-pipeline,cli,python
Classifier: Intended Audience :: Developers
Classifier: Intended Audience :: Science/Research
Classifier: Topic :: Software Development :: Build Tools
Classifier: Topic :: Software Development :: Libraries :: Python Modules
Classifier: Topic :: Software Development :: Libraries
Classifier: Topic :: Utilities
Classifier: Topic :: Scientific/Engineering :: Information Analysis
Classifier: Programming Language :: Python
Classifier: Programming Language :: Python :: 3
Classifier: Programming Language :: Python :: 3.10
Classifier: Programming Language :: Python :: 3.11
Classifier: Programming Language :: Python :: 3.12
Classifier: Programming Language :: Python :: 3 :: Only
Classifier: License :: OSI Approved :: MIT License
Classifier: Operating System :: OS Independent
Classifier: Natural Language :: English
Requires-Python: >=3.10
License-File: LICENSE
Requires-Dist: alembic==1.13.1
Requires-Dist: beautifulsoup4==4.12.3
Requires-Dist: dateparser==1.2.0
Requires-Dist: deep-translator==1.11.4
Requires-Dist: lxml==5.2.2
Requires-Dist: numpy==2.0.0
Requires-Dist: pandas==2.2.2
Requires-Dist: pydantic==2.7.4
Requires-Dist: pydantic-settings==2.3.3
Requires-Dist: pydantic-core==2.18.4
Requires-Dist: PyMySQL==1.1.1
Requires-Dist: python-dotenv==1.0.1
Requires-Dist: PyYAML==6.0.1
Requires-Dist: rich==13.7.1
Requires-Dist: SQLAlchemy==2.0.31
Requires-Dist: tqdm==4.66.4
Requires-Dist: typer==0.12.3
Requires-Dist: Levenshtein==0.25.1
Requires-Dist: fuzzywuzzy==0.18.0
Requires-Dist: python-Levenshtein==0.25.1
Requires-Dist: rapidfuzz==3.9.6
